configurize/__init__.py
configurize/allowed_types.py
configurize/cli.py
configurize/config.py
configurize/data_class.py
configurize/mock_imports.py
configurize/reference.py
configurize/utils.py
configurize-0.1.4.dist-info/licenses/LICENSE
configurize-0.1.4.dist-info/METADATA
configurize-0.1.4.dist-info/WHEEL
configurize-0.1.4.dist-info/entry_points.txt
configurize-0.1.4.dist-info/top_level.txt
configurize-0.1.4.dist-info/RECORD
