Metadata-Version: 2.4
Name: configurize
Version: 0.1.4
Summary: Hierarchical configuration management with inheritance, cross-references, and diffing
Author-email: Zhou Hongyu <rndj@outlook.com>
License: MIT
Project-URL: Homepage, https://github.com/Randomizez/configurize
Project-URL: Repository, https://github.com/Randomizez/configurize
Keywords: config,configuration,settings,hierarchical,dataclass
Classifier: Development Status :: 4 - Beta
Classifier: Intended Audience :: Developers
Classifier: Programming Language :: Python :: 3
Classifier: Programming Language :: Python :: 3.6
Classifier: Programming Language :: Python :: 3.7
Classifier: Programming Language :: Python :: 3.8
Classifier: Programming Language :: Python :: 3.9
Classifier: Programming Language :: Python :: 3.10
Classifier: Programming Language :: Python :: 3.11
Classifier: Programming Language :: Python :: 3.12
Classifier: Topic :: Software Development :: Libraries :: Python Modules
Requires-Python: >=3.6
License-File: LICENSE
Requires-Dist: loguru
Requires-Dist: fire
Dynamic: license-file
